README.md
setup.py
irisdanded_squadcast_pulumi/__init__.py
irisdanded_squadcast_pulumi/_inputs.py
irisdanded_squadcast_pulumi/_utilities.py
irisdanded_squadcast_pulumi/deduplication_rule_v2.py
irisdanded_squadcast_pulumi/escalation_policy.py
irisdanded_squadcast_pulumi/ger.py
irisdanded_squadcast_pulumi/ger_ruleset.py
irisdanded_squadcast_pulumi/ger_ruleset_rule.py
irisdanded_squadcast_pulumi/ger_ruleset_rules_ordering.py
irisdanded_squadcast_pulumi/get_escalation_policy.py
irisdanded_squadcast_pulumi/get_runbook.py
irisdanded_squadcast_pulumi/get_schedule.py
irisdanded_squadcast_pulumi/get_schedule_v2.py
irisdanded_squadcast_pulumi/get_service.py
irisdanded_squadcast_pulumi/get_squad.py
irisdanded_squadcast_pulumi/get_team.py
irisdanded_squadcast_pulumi/get_team_role.py
irisdanded_squadcast_pulumi/get_user.py
irisdanded_squadcast_pulumi/get_webform.py
irisdanded_squadcast_pulumi/outputs.py
irisdanded_squadcast_pulumi/provider.py
irisdanded_squadcast_pulumi/pulumi-plugin.json
irisdanded_squadcast_pulumi/py.typed
irisdanded_squadcast_pulumi/routing_rule_v2.py
irisdanded_squadcast_pulumi/runbook.py
irisdanded_squadcast_pulumi/schedule.py
irisdanded_squadcast_pulumi/schedule_rotation_v2.py
irisdanded_squadcast_pulumi/schedule_v2.py
irisdanded_squadcast_pulumi/service.py
irisdanded_squadcast_pulumi/service_maintenance.py
irisdanded_squadcast_pulumi/slo.py
irisdanded_squadcast_pulumi/squad.py
irisdanded_squadcast_pulumi/status_page.py
irisdanded_squadcast_pulumi/status_page_component.py
irisdanded_squadcast_pulumi/status_page_group.py
irisdanded_squadcast_pulumi/suppression_rule_v2.py
irisdanded_squadcast_pulumi/tagging_rule_v2.py
irisdanded_squadcast_pulumi/team.py
irisdanded_squadcast_pulumi/team_member.py
irisdanded_squadcast_pulumi/team_role.py
irisdanded_squadcast_pulumi/user.py
irisdanded_squadcast_pulumi/webform.py
irisdanded_squadcast_pulumi/workflow.py
irisdanded_squadcast_pulumi/workflow_action.py
irisdanded_squadcast_pulumi/workflow_action_ordering.py
irisdanded_squadcast_pulumi.egg-info/PKG-INFO
irisdanded_squadcast_pulumi.egg-info/SOURCES.txt
irisdanded_squadcast_pulumi.egg-info/dependency_links.txt
irisdanded_squadcast_pulumi.egg-info/not-zip-safe
irisdanded_squadcast_pulumi.egg-info/requires.txt
irisdanded_squadcast_pulumi.egg-info/top_level.txt
