Metadata-Version: 2.1
Name: irisdanded-squadcast-pulumi
Version: 0.1.9
Summary: A Pulumi package for creating and managing Squadcast resources
Home-page: https://github.com/IrisDande/pulumi-squadcast
License: Apache-2.0
Project-URL: Repository, https://github.com/IrisDande/pulumi-squadcast
Keywords: pulumi squadcast category/cloud
Platform: UNKNOWN
Requires-Python: >=3.8
